ezsec/__init__.py
ezsec/ezsec.py
ezsec-0.0.3.dist-info/LICENSE
ezsec-0.0.3.dist-info/METADATA
ezsec-0.0.3.dist-info/WHEEL
ezsec-0.0.3.dist-info/top_level.txt
ezsec-0.0.3.dist-info/RECORD
