Metadata-Version: 2.2
Name: ezsec
Version: 0.0.3
Summary: A small example package
Author-email: maxeffortcode <mbultman@ezsec-api.com>
License: MIT
Project-URL: Homepage, https://github.com/pypa/sampleproject
Project-URL: Issues, https://github.com/pypa/sampleproject/issues
Classifier: Programming Language :: Python :: 3
Classifier: Operating System :: OS Independent
Requires-Python: >=3.8
License-File: LICENSE
Requires-Dist: requests
